unicode_mayo/__init__.py
unicode_mayo/tests/__init__.py
unicode_mayo/tests/test_unicode_mayo.py
unicode_mayo-1.1.0.dist-info/LICENSE
unicode_mayo-1.1.0.dist-info/METADATA
unicode_mayo-1.1.0.dist-info/WHEEL
unicode_mayo-1.1.0.dist-info/top_level.txt
unicode_mayo-1.1.0.dist-info/zip-safe
unicode_mayo-1.1.0.dist-info/RECORD
