Metadata-Version: 2.1
Name: unicode-mayo
Version: 1.1.0
Summary: The mayo on your unicode sandwich
Home-page: https://github.com/eyalr/unicode_mayo
Author: UNKNOWN
Author-email: UNKNOWN
License: MIT
Platform: UNKNOWN
Classifier: License :: OSI Approved :: MIT License
Classifier: Programming Language :: Python :: 2.6
Classifier: Programming Language :: Python :: 2.7
